{
  "extractedAt": "2026-02-26T10:20:02.721Z",
  "count": 61,
  "items": [
    {
      "name": "Liberator Shield",
      "levelReq": 1,
      "defense": 0.6,
      "dexterity": null,
      "worth": 1,
      "howToObtain": "Floor 1 Shop, Requires [[Grandmaster Liberator Gamepass]",
      "raw": {
        "title1": "Liberator Shield",
        "image1": "Liberator_Shield.png",
        "equipment_type": "Shields",
        "level_req": "Level 1 [Min]\nLevel 160 [Max]",
        "defense": "0.6 [Min]\n167.4 [Max]",
        "craftable": "X",
        "tradable": "X",
        "worth": "1 Col",
        "can_be_sold": "X",
        "how_to_obtain": "Floor 1 Shop, Requires [[Grandmaster Liberator Gamepass]"
      },
      "wikiTitle": "Liberator Shield",
      "wikiUrl": "https://swordbloxonlinerebirth.fandom.com/wiki/Liberator_Shield",
      "slot": "shield"
    },
    {
      "name": "Steel Shield",
      "levelReq": 5,
      "defense": 1.5,
      "dexterity": null,
      "worth": 1900,
      "howToObtain": "Floor 1 Shop, [[Shops#Floor 2 Shop|Floor 2 Shop]",
      "raw": {
        "title1": "Steel Shield",
        "image1": "Steel shield.png",
        "level_req": "Level 5",
        "craftable": "X",
        "tradable": "✔",
        "defense": "1.5",
        "equipment_type": "Shields",
        "worth": "1900 Col",
        "can_be_sold": "✔",
        "how_to_obtain": "Floor 1 Shop, [[Shops#Floor 2 Shop|Floor 2 Shop]"
      },
      "wikiTitle": "Steel Shield",
      "wikiUrl": "https://swordbloxonlinerebirth.fandom.com/wiki/Steel_Shield",
      "slot": "shield"
    },
    {
      "name": "Obsidiguard",
      "levelReq": 60,
      "defense": 37.2,
      "dexterity": null,
      "worth": 22800,
      "howToObtain": "Floor 5 Shop",
      "raw": {
        "title1": "Obsidiguard",
        "image1": "Obsidiguard.png",
        "level_req": "Level 60",
        "craftable": "X",
        "tradable": "✔",
        "defense": "37.2",
        "equipment_type": "Shields",
        "worth": "22800 Col",
        "can_be_sold": "✔",
        "how_to_obtain": "Floor 5 Shop"
      },
      "wikiTitle": "Obsidiguard",
      "wikiUrl": "https://swordbloxonlinerebirth.fandom.com/wiki/Obsidiguard",
      "slot": "shield"
    },
    {
      "name": "Knights Shield",
      "levelReq": 18,
      "defense": 7.2,
      "dexterity": null,
      "worth": 6840,
      "howToObtain": "Floor 2 Shop, Floor 3 Shop",
      "raw": {
        "title1": "Knights Shield",
        "image1": "Knights shield.png",
        "level_req": "Level 18",
        "craftable": "X",
        "tradable": "✔",
        "defense": "7.2",
        "equipment_type": "Shields",
        "worth": "6840 Col",
        "can_be_sold": "✔",
        "how_to_obtain": "Floor 2 Shop, Floor 3 Shop"
      },
      "wikiTitle": "Knights Shield",
      "wikiUrl": "https://swordbloxonlinerebirth.fandom.com/wiki/Knights_Shield",
      "slot": "shield"
    },
    {
      "name": "Malachite Shield",
      "levelReq": 35,
      "defense": 18,
      "dexterity": null,
      "worth": 13300,
      "howToObtain": "[[Blacksmithing",
      "raw": {
        "title1": "Malachite Shield",
        "image1": "Malachite shield.png",
        "level_req": "Level 35",
        "craftable": "X",
        "tradable": "✔",
        "defense": "18",
        "equipment_type": "Shields",
        "worth": "13300 Col",
        "can_be_sold": "✔",
        "how_to_obtain": "[[Blacksmithing"
      },
      "wikiTitle": "Malachite Shield",
      "wikiUrl": "https://swordbloxonlinerebirth.fandom.com/wiki/Malachite_Shield",
      "slot": "shield"
    },
    {
      "name": "IronClad",
      "levelReq": 45,
      "defense": 25.2,
      "dexterity": null,
      "worth": 17100,
      "howToObtain": "Floor 1 Shop",
      "raw": {
        "title1": "IronClad",
        "image1": "Ironclad.png",
        "level_req": "Level 45",
        "craftable": "X",
        "tradable": "✔",
        "defense": "25.2",
        "equipment_type": "Shields",
        "worth": "17100 Col",
        "can_be_sold": "✔",
        "how_to_obtain": "Floor 1 Shop"
      },
      "wikiTitle": "IronClad",
      "wikiUrl": "https://swordbloxonlinerebirth.fandom.com/wiki/IronClad",
      "slot": "shield"
    },
    {
      "name": "Mirror Shield",
      "levelReq": 50,
      "defense": 29.1,
      "dexterity": null,
      "worth": 19000,
      "howToObtain": "Floor 5 Shop",
      "raw": {
        "title1": "Mirror Shield",
        "image1": "Mirror shield.png",
        "level_req": "Level 50",
        "craftable": "X",
        "tradable": "✔",
        "defense": "29.1",
        "equipment_type": "Shields",
        "worth": "19000 Col",
        "can_be_sold": "✔",
        "how_to_obtain": "Floor 5 Shop"
      },
      "wikiTitle": "Mirror Shield",
      "wikiUrl": "https://swordbloxonlinerebirth.fandom.com/wiki/Mirror_Shield",
      "slot": "shield"
    },
    {
      "name": "Comedy Tragic",
      "levelReq": 110,
      "defense": 84.9,
      "dexterity": null,
      "worth": 41800,
      "howToObtain": "Floor 10 Shop",
      "raw": {
        "title1": "Comedy Tragic",
        "image1": "Comedy tragic.png",
        "level_req": "Level 110",
        "craftable": "X",
        "tradable": "✔",
        "defense": "84.9",
        "equipment_type": "Shields",
        "worth": "41800 Col",
        "can_be_sold": "✔",
        "how_to_obtain": "Floor 10 Shop"
      },
      "wikiTitle": "Comedy Tragic",
      "wikiUrl": "https://swordbloxonlinerebirth.fandom.com/wiki/Comedy_Tragic",
      "slot": "shield"
    },
    {
      "name": "Ancient Guardian",
      "levelReq": 80,
      "defense": 55.2,
      "dexterity": null,
      "worth": 30400,
      "howToObtain": "[[Blacksmithing",
      "raw": {
        "title1": "Ancient Guardian",
        "image1": "Ancient guardian.png",
        "level_req": "Level 80",
        "craftable": "✔",
        "tradable": "✔",
        "defense": "55.2",
        "equipment_type": "Shields",
        "worth": "30400 Col",
        "can_be_sold": "✔",
        "how_to_obtain": "[[Blacksmithing"
      },
      "wikiTitle": "Ancient Guardian",
      "wikiUrl": "https://swordbloxonlinerebirth.fandom.com/wiki/Ancient_Guardian",
      "slot": "shield"
    },
    {
      "name": "Krakens Skin",
      "levelReq": 105,
      "defense": 79.8,
      "dexterity": null,
      "worth": 39900,
      "howToObtain": "[[Karth'uk The Crystal Kraken",
      "raw": {
        "title1": "Krakens Skin",
        "image1": "Krakens skin.png",
        "level_req": "Level 105",
        "craftable": "X",
        "tradable": "✔",
        "defense": "79.8",
        "equipment_type": "Shields",
        "worth": "39900 Col",
        "can_be_sold": "✔",
        "how_to_obtain": "[[Karth'uk The Crystal Kraken"
      },
      "wikiTitle": "Krakens Skin",
      "wikiUrl": "https://swordbloxonlinerebirth.fandom.com/wiki/Krakens_Skin",
      "slot": "shield"
    },
    {
      "name": "Arachnophobias Shield",
      "levelReq": 80,
      "defense": 55.2,
      "dexterity": null,
      "worth": 30400,
      "howToObtain": "[[Arachnophobia",
      "raw": {
        "title1": "Arachnophobias Shield",
        "image1": "Coom shield.png",
        "level_req": "Level 80",
        "craftable": "X",
        "tradable": "✔",
        "defense": "55.2",
        "equipment_type": "Shields",
        "worth": "30400 Col",
        "can_be_sold": "✔",
        "how_to_obtain": "[[Arachnophobia"
      },
      "wikiTitle": "Arachnophobias Shield",
      "wikiUrl": "https://swordbloxonlinerebirth.fandom.com/wiki/Arachnophobias_Shield",
      "slot": "shield"
    },
    {
      "name": "Golden Shield",
      "levelReq": 95,
      "defense": 69.6,
      "dexterity": null,
      "worth": 36100,
      "howToObtain": "Floor 10 Shop",
      "raw": {
        "title1": "Golden Shield",
        "image1": "Golden shield.png",
        "craftable": "X",
        "tradable": "✔",
        "level_req": "Level 95",
        "defense": "69.6",
        "equipment_type": "Shields",
        "worth": "36100 Col",
        "can_be_sold": "✔",
        "how_to_obtain": "Floor 10 Shop"
      },
      "wikiTitle": "Golden Shield",
      "wikiUrl": "https://swordbloxonlinerebirth.fandom.com/wiki/Golden_Shield",
      "slot": "shield"
    },
    {
      "name": "Laurel Shield",
      "levelReq": 122,
      "defense": 97.8,
      "dexterity": null,
      "worth": 46360,
      "howToObtain": "[[Knight",
      "raw": {
        "title1": "Laurel Shield",
        "image1": "Laurel shield.png",
        "level_req": "Level 122",
        "craftable": "X",
        "tradable": "✔",
        "defense": "97.8",
        "equipment_type": "Shields",
        "worth": "46360 Col",
        "can_be_sold": "✔",
        "how_to_obtain": "[[Knight"
      },
      "wikiTitle": "Laurel Shield",
      "wikiUrl": "https://swordbloxonlinerebirth.fandom.com/wiki/Laurel_Shield",
      "slot": "shield"
    },
    {
      "name": "Pepperment Shield MK I",
      "levelReq": 100,
      "defense": 74.7,
      "dexterity": null,
      "worth": 38000,
      "howToObtain": "Christmas Event: Event Quest Rewa",
      "raw": {
        "title1": "Pepperment Shield MK I",
        "image1": "Peppermint shield.png",
        "level_req": "Level 100",
        "craftable": "X",
        "tradable": "✔",
        "defense": "74.7",
        "equipment_type": "Shields",
        "worth": "38000 Col",
        "can_be_sold": "✔",
        "how_to_obtain": "Christmas Event: Event Quest Rewa"
      },
      "wikiTitle": "Peppermint Shield MK I",
      "wikiUrl": "https://swordbloxonlinerebirth.fandom.com/wiki/Peppermint_Shield_MK_I",
      "slot": "shield"
    },
    {
      "name": "Floral Shield",
      "levelReq": 120,
      "defense": 95.4,
      "dexterity": null,
      "worth": 45600,
      "howToObtain": "Floor 12 Shop",
      "raw": {
        "title1": "Floral Shield",
        "image1": "Floral shield.png",
        "level_req": "Level 120",
        "craftable": "X",
        "tradable": "✔",
        "defense": "95.4",
        "equipment_type": "Shields",
        "worth": "45600 Col",
        "can_be_sold": "✔",
        "how_to_obtain": "Floor 12 Shop"
      },
      "wikiTitle": "Floral Shield",
      "wikiUrl": "https://swordbloxonlinerebirth.fandom.com/wiki/Floral_Shield",
      "slot": "shield"
    },
    {
      "name": "Peppermint Shield MK II",
      "levelReq": 192,
      "defense": 180.6,
      "dexterity": null,
      "worth": 76000,
      "howToObtain": "Christmas Event: [[Blacksmithing]",
      "raw": {
        "title1": "Peppermint Shield MK II",
        "image1": "Super peppermint shield.png",
        "equipment_type": "Shields",
        "level_req": "Level 192",
        "defense": "180.6",
        "craftable": "✔",
        "tradable": "✔",
        "worth": "76000 Col",
        "can_be_sold": "✔",
        "how_to_obtain": "Christmas Event: [[Blacksmithing]"
      },
      "wikiTitle": "Peppermint Shield MK II",
      "wikiUrl": "https://swordbloxonlinerebirth.fandom.com/wiki/Peppermint_Shield_MK_II",
      "slot": "shield"
    },
    {
      "name": "Arachnophobias Shield MK II",
      "levelReq": 160,
      "defense": 141,
      "dexterity": null,
      "worth": 60800,
      "howToObtain": "Halloween Event: [[Blacksmithing",
      "raw": {
        "title1": "Arachnophobias Shield MK II",
        "image1": "Coom shield mark 2.jpeg",
        "level_req": "Level 160",
        "craftable": "✔",
        "tradable": "✔",
        "defense": "141",
        "equipment_type": "Shields",
        "worth": "60800 Col",
        "can_be_sold": "✔",
        "how_to_obtain": "Halloween Event: [[Blacksmithing"
      },
      "wikiTitle": "Arachnophobias Shield MK II",
      "wikiUrl": "https://swordbloxonlinerebirth.fandom.com/wiki/Arachnophobias_Shield_MK_II",
      "slot": "shield"
    },
    {
      "name": "Cornucopia Shield Mk I",
      "levelReq": 90,
      "defense": 64.8,
      "dexterity": null,
      "worth": 200,
      "howToObtain": "Thanksgiving Event: Thanksgiving Shop [2021-2022 Only], Blacksmithin",
      "raw": {
        "title1": "Cornucopia Shield Mk I",
        "image1": "Cornucopia shield.png",
        "equipment_type": "Shields",
        "level_req": "Level 90",
        "defense": "64.8",
        "craftable": "X",
        "tradable": "✔",
        "worth": "200 Turkey Feather",
        "can_be_sold": "X",
        "how_to_obtain": "Thanksgiving Event: Thanksgiving Shop [2021-2022 Only], Blacksmithin"
      },
      "wikiTitle": "Cornucopia Shield Mk I",
      "wikiUrl": "https://swordbloxonlinerebirth.fandom.com/wiki/Cornucopia_Shield_Mk_I",
      "slot": "shield"
    },
    {
      "name": "Cornucopia Shield Mk II",
      "levelReq": 180,
      "defense": 165.3,
      "dexterity": null,
      "worth": 275,
      "howToObtain": "Thanksgiving Event: [[Blacksmithing",
      "raw": {
        "title1": "Cornucopia Shield Mk II",
        "image1": "Cornucopia shield mk2.png",
        "level_req": "Level 180",
        "craftable": "✔",
        "tradable": "✔",
        "defense": "165.3",
        "equipment_type": "Shields",
        "worth": "275 Turkey Feather",
        "can_be_sold": "X",
        "how_to_obtain": "Thanksgiving Event: [[Blacksmithing"
      },
      "wikiTitle": "Cornucopia Shield Mk II",
      "wikiUrl": "https://swordbloxonlinerebirth.fandom.com/wiki/Cornucopia_Shield_Mk_II",
      "slot": "shield"
    },
    {
      "name": "Permafrost Shield",
      "levelReq": 55,
      "defense": 33.3,
      "dexterity": null,
      "worth": 20900,
      "howToObtain": "[[Blacksmithing",
      "raw": {
        "title1": "Permafrost Shield",
        "image1": "PermafrostShield.png",
        "level_req": "Level 55",
        "craftable": "✔",
        "tradable": "✔",
        "defense": "33.3",
        "equipment_type": "Shields",
        "worth": "20900 Col",
        "can_be_sold": "✔",
        "how_to_obtain": "[[Blacksmithing"
      },
      "wikiTitle": "Permafrost Shield",
      "wikiUrl": "https://swordbloxonlinerebirth.fandom.com/wiki/Permafrost_Shield",
      "slot": "shield"
    },
    {
      "name": "GrandMaster Shield",
      "levelReq": 16,
      "defense": 6.3,
      "dexterity": null,
      "worth": 6080,
      "howToObtain": "[[Shadesworn the Corrupted",
      "raw": {
        "title1": "GrandMaster Shield",
        "image1": "GrandMasterShield.png",
        "level_req": "Level 16",
        "craftable": "X",
        "tradable": "✔",
        "defense": "6.3",
        "equipment_type": "Shields",
        "worth": "6080 Col",
        "can_be_sold": "✔",
        "how_to_obtain": "[[Shadesworn the Corrupted"
      },
      "wikiTitle": "GrandMaster Shield",
      "wikiUrl": "https://swordbloxonlinerebirth.fandom.com/wiki/GrandMaster_Shield",
      "slot": "shield"
    },
    {
      "name": "Illfangs Shield",
      "levelReq": 26,
      "defense": 12,
      "dexterity": null,
      "worth": 9880,
      "howToObtain": "[[Illfang The Kobold Lord",
      "raw": {
        "title1": "Illfangs Shield",
        "image1": "IllfangsShield.png",
        "level_req": "Level 26",
        "craftable": "X",
        "tradable": "✔",
        "defense": "12",
        "equipment_type": "Shields",
        "worth": "9880 Col",
        "can_be_sold": "✔",
        "how_to_obtain": "[[Illfang The Kobold Lord"
      },
      "wikiTitle": "Illfangs Shield",
      "wikiUrl": "https://swordbloxonlinerebirth.fandom.com/wiki/Illfangs_Shield",
      "slot": "shield"
    },
    {
      "name": "Cursed Shield",
      "levelReq": 127,
      "defense": 103.2,
      "dexterity": null,
      "worth": 48260,
      "howToObtain": "[[Tormented Spectrum",
      "raw": {
        "title1": "Cursed Shield",
        "image1": "Cursed Shield.png",
        "level_req": "Level 127",
        "craftable": "X",
        "tradable": "✔",
        "defense": "103.2",
        "equipment_type": "Shields",
        "worth": "48260 Col",
        "can_be_sold": "✔",
        "how_to_obtain": "[[Tormented Spectrum"
      },
      "wikiTitle": "Cursed Shield",
      "wikiUrl": "https://swordbloxonlinerebirth.fandom.com/wiki/Cursed_Shield",
      "slot": "shield"
    },
    {
      "name": "Stone Shield",
      "levelReq": 90,
      "defense": 64.8,
      "dexterity": null,
      "worth": 34200,
      "howToObtain": "[[Bonnz the Skeleton Lord",
      "raw": {
        "title1": "Stone Shield",
        "image1": "Stone Shield.png",
        "level_req": "Level 90",
        "craftable": "X",
        "tradable": "✔",
        "defense": "64.8",
        "equipment_type": "Shields",
        "worth": "34200 Col",
        "can_be_sold": "✔",
        "how_to_obtain": "[[Bonnz the Skeleton Lord"
      },
      "wikiTitle": "Stone Shield",
      "wikiUrl": "https://swordbloxonlinerebirth.fandom.com/wiki/Stone_Shield",
      "slot": "shield"
    },
    {
      "name": "Master Shield",
      "levelReq": 10,
      "defense": 3.3,
      "dexterity": null,
      "worth": 3800,
      "howToObtain": "Floor 1 Shop, Floor 2 Shop",
      "raw": {
        "title1": "Master Shield",
        "image1": "Master Shield.png",
        "level_req": "Level 10",
        "craftable": "✔",
        "tradable": "✔",
        "defense": "3.3",
        "equipment_type": "Shields",
        "worth": "3800 Col",
        "can_be_sold": "✔",
        "how_to_obtain": "Floor 1 Shop, Floor 2 Shop"
      },
      "wikiTitle": "Master Shield",
      "wikiUrl": "https://swordbloxonlinerebirth.fandom.com/wiki/Master_Shield",
      "slot": "shield"
    },
    {
      "name": "Aquatic Guard",
      "levelReq": 85,
      "defense": 60,
      "dexterity": null,
      "worth": 32300,
      "howToObtain": "Floor 9 Hidden Shop",
      "raw": {
        "title1": "Aquatic Guard",
        "image1": "Aquatic Guard.png",
        "level_req": "Level 85",
        "craftable": "X",
        "tradable": "✔",
        "defense": "60",
        "equipment_type": "Shields",
        "worth": "32300 Col",
        "can_be_sold": "✔",
        "how_to_obtain": "Floor 9 Hidden Shop"
      },
      "wikiTitle": "Aquatic Guard",
      "wikiUrl": "https://swordbloxonlinerebirth.fandom.com/wiki/Aquatic_Guard",
      "slot": "shield"
    },
    {
      "name": "Royal Guard",
      "levelReq": 115,
      "defense": 90.3,
      "dexterity": null,
      "worth": 43700,
      "howToObtain": "Floor 10 Shop",
      "raw": {
        "title1": "Royal Guard",
        "image1": "Royal Guard.png",
        "craftable": "X",
        "tradable": "✔",
        "level_req": "Level 115",
        "defense": "90.3",
        "equipment_type": "Shields",
        "worth": "43700 Col",
        "can_be_sold": "✔",
        "how_to_obtain": "Floor 10 Shop"
      },
      "wikiTitle": "Royal Guard",
      "wikiUrl": "https://swordbloxonlinerebirth.fandom.com/wiki/Royal_Guard",
      "slot": "shield"
    },
    {
      "name": "Sky Shield",
      "levelReq": 135,
      "defense": 112.2,
      "dexterity": null,
      "worth": 51300,
      "howToObtain": "Quest #66 Reward",
      "raw": {
        "title1": "Sky Shield",
        "image1": "Sky Shield.png",
        "level_req": "Level 135",
        "craftable": "X",
        "tradable": "✔",
        "defense": "112.2",
        "equipment_type": "Shields",
        "worth": "51300 Col",
        "can_be_sold": "✔",
        "how_to_obtain": "Quest #66 Reward"
      },
      "wikiTitle": "Sky Shield",
      "wikiUrl": "https://swordbloxonlinerebirth.fandom.com/wiki/Sky_Shield",
      "slot": "shield"
    },
    {
      "name": "Magic Guard",
      "levelReq": 138,
      "defense": 115.5,
      "dexterity": null,
      "worth": 52440,
      "howToObtain": "Quest #68 Reward",
      "raw": {
        "title1": "Magic Guard",
        "image1": "Magic Guard.png",
        "level_req": "Level 138",
        "craftable": "X",
        "tradable": "✔",
        "defense": "115.5",
        "equipment_type": "Shields",
        "worth": "52440 Col",
        "can_be_sold": "✔",
        "how_to_obtain": "Quest #68 Reward"
      },
      "wikiTitle": "Magic Guard",
      "wikiUrl": "https://swordbloxonlinerebirth.fandom.com/wiki/Magic_Guard",
      "slot": "shield"
    },
    {
      "name": "Divine Guard",
      "levelReq": 148,
      "defense": 126.9,
      "dexterity": null,
      "worth": 56240,
      "howToObtain": "[[Young Celestia",
      "raw": {
        "title1": "Divine Guard",
        "image1": "Divine Guard.png",
        "level_req": "Level 148",
        "craftable": "X",
        "tradable": "X",
        "defense": "126.9",
        "equipment_type": "Shields",
        "worth": "56240 Col",
        "can_be_sold": "X",
        "how_to_obtain": "[[Young Celestia"
      },
      "wikiTitle": "Divine Guard",
      "wikiUrl": "https://swordbloxonlinerebirth.fandom.com/wiki/Divine_Guard",
      "slot": "shield"
    },
    {
      "name": "Easter Island Shield Mk II",
      "levelReq": 160,
      "defense": 141,
      "dexterity": null,
      "worth": 280,
      "howToObtain": "Easter Event: [[Blacksmithing",
      "raw": {
        "title1": "Easter Island Shield Mk II",
        "image1": "Easter Island Shield Mk II.png",
        "level_req": "Level 160",
        "craftable": "✔",
        "tradable": "✔",
        "defense": "141",
        "equipment_type": "Shields",
        "worth": "280 Easter Egg",
        "can_be_sold": "X",
        "how_to_obtain": "Easter Event: [[Blacksmithing"
      },
      "wikiTitle": "Easter Island Shield Mk II",
      "wikiUrl": "https://swordbloxonlinerebirth.fandom.com/wiki/Easter_Island_Shield_Mk_II",
      "slot": "shield"
    },
    {
      "name": "GrandMaster Shield Mk II",
      "levelReq": 20,
      "defense": 8.4,
      "dexterity": null,
      "worth": 7600,
      "howToObtain": "[[Blacksmithing",
      "raw": {
        "title1": "GrandMaster Shield Mk II",
        "image1": "GM shield mk II.png",
        "level_req": "Level 20",
        "craftable": "✔",
        "tradable": "✔",
        "defense": "8.4",
        "equipment_type": "Shields",
        "worth": "7600 Col",
        "can_be_sold": "✔",
        "how_to_obtain": "[[Blacksmithing"
      },
      "wikiTitle": "GrandMaster Shield Mk II",
      "wikiUrl": "https://swordbloxonlinerebirth.fandom.com/wiki/GrandMaster_Shield_Mk_II",
      "slot": "shield"
    },
    {
      "name": "Easter Egg Shield",
      "levelReq": 1,
      "defense": 0.6,
      "dexterity": null,
      "worth": 275,
      "howToObtain": "[[Demented Bunny",
      "raw": {
        "title1": "Easter Egg Shield",
        "image1": "Easter Egg Shield.png",
        "level_req": "Level 1 [Min]\nLevel 150 [Max]",
        "craftable": "X",
        "tradable": "X",
        "defense": "0.6 [Min]\n137.4 [Max]",
        "equipment_type": "Shields",
        "worth": "275 Easter Egg",
        "can_be_sold": "X",
        "how_to_obtain": "[[Demented Bunny"
      },
      "wikiTitle": "Easter Egg Shield",
      "wikiUrl": "https://swordbloxonlinerebirth.fandom.com/wiki/Easter_Egg_Shield",
      "slot": "shield"
    },
    {
      "name": "Easter Island Shield",
      "levelReq": 80,
      "defense": 55.2,
      "dexterity": null,
      "worth": 140,
      "howToObtain": "Easter Event: Holiday Sh",
      "raw": {
        "title1": "Easter Island Shield",
        "image1": "Easter Island Shield.png",
        "level_req": "Level 80",
        "craftable": "X",
        "tradable": "✔",
        "defense": "55.2",
        "equipment_type": "Shields",
        "worth": "140 Easter Egg",
        "can_be_sold": "X",
        "how_to_obtain": "Easter Event: Holiday Sh"
      },
      "wikiTitle": "Easter Island Shield",
      "wikiUrl": "https://swordbloxonlinerebirth.fandom.com/wiki/Easter_Island_Shield",
      "slot": "shield"
    },
    {
      "name": "College Protection",
      "levelReq": 142,
      "defense": 120,
      "dexterity": null,
      "worth": 53960,
      "howToObtain": "Floor 15 Shop",
      "raw": {
        "title1": "College Protection",
        "image1": "College Protection.png",
        "level_req": "Level 142",
        "craftable": "X",
        "tradable": "✔",
        "defense": "120",
        "equipment_type": "Shields",
        "worth": "53960 Col",
        "can_be_sold": "✔",
        "how_to_obtain": "Floor 15 Shop"
      },
      "wikiTitle": "College Protection",
      "wikiUrl": "https://swordbloxonlinerebirth.fandom.com/wiki/College_Protection",
      "slot": "shield"
    },
    {
      "name": "Broken Wood Shield",
      "levelReq": 147,
      "defense": 125.7,
      "dexterity": null,
      "worth": 55860,
      "howToObtain": "Floor 16 Shop",
      "raw": {
        "title1": "Broken Wood Shield",
        "image1": "Broken Wood Shield.png",
        "level_req": "Level 147",
        "craftable": "X",
        "tradable": "✔",
        "defense": "125.7",
        "equipment_type": "Shields",
        "worth": "55860 Col",
        "can_be_sold": "✔",
        "how_to_obtain": "Floor 16 Shop"
      },
      "wikiTitle": "Broken Wood Shield",
      "wikiUrl": "https://swordbloxonlinerebirth.fandom.com/wiki/Broken_Wood_Shield",
      "slot": "shield"
    },
    {
      "name": "Master Shield Mk II",
      "levelReq": 13,
      "defense": 4.8,
      "dexterity": null,
      "worth": 4940,
      "howToObtain": "[[Blacksmithing",
      "raw": {
        "title1": "Master Shield Mk II",
        "image1": "Master Shield Mk II.png",
        "level_req": "Level 13",
        "craftable": "✔",
        "tradable": "✔",
        "defense": "4.8",
        "equipment_type": "Shields",
        "worth": "4940 Col",
        "can_be_sold": "✔",
        "how_to_obtain": "[[Blacksmithing"
      },
      "wikiTitle": "Master Shield Mk II",
      "wikiUrl": "https://swordbloxonlinerebirth.fandom.com/wiki/Master_Shield_Mk_II",
      "slot": "shield"
    },
    {
      "name": "GrandMaster Shield Mk III",
      "levelReq": 24,
      "defense": 10.8,
      "dexterity": null,
      "worth": 9120,
      "howToObtain": "[[Blacksmithing",
      "raw": {
        "title1": "GrandMaster Shield Mk III",
        "image1": "GrandMaster Shield Mk III.png",
        "level_req": "Level 24",
        "craftable": "✔",
        "tradable": "✔",
        "defense": "10.8",
        "equipment_type": "Shields",
        "worth": "9120 Col",
        "can_be_sold": "✔",
        "how_to_obtain": "[[Blacksmithing"
      },
      "wikiTitle": "GrandMaster Shield Mk III",
      "wikiUrl": "https://swordbloxonlinerebirth.fandom.com/wiki/GrandMaster_Shield_Mk_III",
      "slot": "shield"
    },
    {
      "name": "Summer Atlantean Shield",
      "levelReq": 35,
      "defense": 18,
      "dexterity": null,
      "worth": 140,
      "howToObtain": "Summer Event: Summer Sho",
      "raw": {
        "title1": "Summer Atlantean Shield",
        "image1": "Summer Atlantean Shield.png",
        "equipment_type": "Shields",
        "level_req": "Level 35",
        "defense": "18",
        "craftable": "X",
        "tradable": "✔",
        "worth": "140 Seashell",
        "can_be_sold": "X",
        "how_to_obtain": "Summer Event: Summer Sho"
      },
      "wikiTitle": "Summer Atlantean Shield",
      "wikiUrl": "https://swordbloxonlinerebirth.fandom.com/wiki/Summer_Atlantean_Shield",
      "slot": "shield"
    },
    {
      "name": "Summer Atlantean Shield Mk II",
      "levelReq": 70,
      "defense": 45.9,
      "dexterity": null,
      "worth": 240,
      "howToObtain": "Summer Event: Blacksmithin",
      "raw": {
        "title1": "Summer Atlantean Shield Mk II",
        "image1": "Summer Atlantean Shield Mk II.png",
        "equipment_type": "Shields",
        "level_req": "Level 70",
        "defense": "45.9",
        "craftable": "✔",
        "tradable": "✔",
        "worth": "240 Seashell",
        "can_be_sold": "X",
        "how_to_obtain": "Summer Event: Blacksmithin"
      },
      "wikiTitle": "Summer Atlantean Shield Mk II",
      "wikiUrl": "https://swordbloxonlinerebirth.fandom.com/wiki/Summer_Atlantean_Shield_Mk_II",
      "slot": "shield"
    },
    {
      "name": "Cornucopia Shield Mk III",
      "levelReq": 190,
      "defense": 177.9,
      "dexterity": null,
      "worth": 350,
      "howToObtain": "Thanksgiving Event: [[Blacksmithing]",
      "raw": {
        "title1": "Cornucopia Shield Mk III",
        "image1": "Cornucopia Shield Mk III.png",
        "level_req": "Level 190",
        "craftable": "✔",
        "tradable": "✔",
        "defense": "177.9",
        "equipment_type": "Shields",
        "worth": "350 Turkey Feather",
        "can_be_sold": "X",
        "how_to_obtain": "Thanksgiving Event: [[Blacksmithing]"
      },
      "wikiTitle": "Cornucopia Shield Mk III",
      "wikiUrl": "https://swordbloxonlinerebirth.fandom.com/wiki/Cornucopia_Shield_Mk_III",
      "slot": "shield"
    },
    {
      "name": "{{PAGENAME}}",
      "levelReq": 170,
      "defense": 153,
      "dexterity": null,
      "worth": null,
      "howToObtain": "[[Blacksmithing]",
      "raw": {
        "title1": "{{PAGENAME}}",
        "image1": "{{PAGENAME}}.png",
        "equipment_type": "Shields",
        "level_req": "Level 170",
        "defense": "153",
        "dexterity": "",
        "craftable": "✔",
        "tradable": "✔",
        "worth": "",
        "can_be_sold": "✔",
        "how_to_obtain": "[[Blacksmithing]"
      },
      "wikiTitle": "Protocol Aegis",
      "wikiUrl": "https://swordbloxonlinerebirth.fandom.com/wiki/Protocol_Aegis",
      "slot": "shield"
    },
    {
      "name": "{{PAGENAME}}",
      "levelReq": 160,
      "defense": 141,
      "dexterity": null,
      "worth": null,
      "howToObtain": "[[Blacksmithing]",
      "raw": {
        "title1": "{{PAGENAME}}",
        "image1": "{{PAGENAME}}.png",
        "equipment_type": "Shields",
        "level_req": "Level 160",
        "defense": "141",
        "dexterity": "",
        "craftable": "✔",
        "tradable": "✔",
        "worth": "",
        "can_be_sold": "✔",
        "how_to_obtain": "[[Blacksmithing]"
      },
      "wikiTitle": "Makeshift Riot Guard",
      "wikiUrl": "https://swordbloxonlinerebirth.fandom.com/wiki/Makeshift_Riot_Guard",
      "slot": "shield"
    },
    {
      "name": "{{PAGENAME}}",
      "levelReq": 40,
      "defense": 21.6,
      "dexterity": null,
      "worth": null,
      "howToObtain": "Easter Event: Blacksmithing Tiered Craftabl",
      "raw": {
        "title1": "{{PAGENAME}}",
        "image1": "{{PAGENAME}}.png",
        "level_req": "Level 40",
        "craftable": "✔",
        "tradable": "✔",
        "defense": "21.6",
        "equipment_type": "Shields",
        "can_be_sold": "X",
        "how_to_obtain": "Easter Event: Blacksmithing Tiered Craftabl"
      },
      "wikiTitle": "Easter Royale Shield",
      "wikiUrl": "https://swordbloxonlinerebirth.fandom.com/wiki/Easter_Royale_Shield",
      "slot": "shield"
    },
    {
      "name": "{{PAGENAME}}",
      "levelReq": 78,
      "defense": 53.4,
      "dexterity": null,
      "worth": null,
      "howToObtain": "Easter Event: Blacksmithing Tiered Craftabl",
      "raw": {
        "title1": "{{PAGENAME}}",
        "image1": "{{PAGENAME}}.png",
        "level_req": "Level 78",
        "craftable": "✔",
        "tradable": "✔",
        "defense": "53.4",
        "equipment_type": "Shields",
        "can_be_sold": "X",
        "how_to_obtain": "Easter Event: Blacksmithing Tiered Craftabl"
      },
      "wikiTitle": "Easter Royale Shield Mk II",
      "wikiUrl": "https://swordbloxonlinerebirth.fandom.com/wiki/Easter_Royale_Shield_Mk_II",
      "slot": "shield"
    },
    {
      "name": "{{PAGENAME}}",
      "levelReq": 116,
      "defense": 91.2,
      "dexterity": null,
      "worth": null,
      "howToObtain": "Easter Event: Blacksmithing Tiered Craftabl",
      "raw": {
        "title1": "{{PAGENAME}}",
        "image1": "{{PAGENAME}}.png",
        "level_req": "Level 116",
        "craftable": "✔",
        "tradable": "✔",
        "defense": "91.2",
        "equipment_type": "Shields",
        "can_be_sold": "X",
        "how_to_obtain": "Easter Event: Blacksmithing Tiered Craftabl"
      },
      "wikiTitle": "Easter Royale Shield Mk III",
      "wikiUrl": "https://swordbloxonlinerebirth.fandom.com/wiki/Easter_Royale_Shield_Mk_III",
      "slot": "shield"
    },
    {
      "name": "{{PAGENAME}}",
      "levelReq": 154,
      "defense": 133.8,
      "dexterity": null,
      "worth": null,
      "howToObtain": "Easter Event: Blacksmithing Tiered Craftabl",
      "raw": {
        "title1": "{{PAGENAME}}",
        "image1": "{{PAGENAME}}.png",
        "level_req": "Level 154",
        "craftable": "✔",
        "tradable": "✔",
        "defense": "133.8",
        "equipment_type": "Shields",
        "can_be_sold": "X",
        "how_to_obtain": "Easter Event: Blacksmithing Tiered Craftabl"
      },
      "wikiTitle": "Easter Royale Shield Mk IV",
      "wikiUrl": "https://swordbloxonlinerebirth.fandom.com/wiki/Easter_Royale_Shield_Mk_IV",
      "slot": "shield"
    },
    {
      "name": "{{PAGENAME}}",
      "levelReq": 192,
      "defense": 180.6,
      "dexterity": null,
      "worth": null,
      "howToObtain": "Easter Event: Blacksmithing Tiered Craftabl",
      "raw": {
        "title1": "{{PAGENAME}}",
        "image1": "{{PAGENAME}}.png",
        "level_req": "Level 192",
        "craftable": "✔",
        "tradable": "✔",
        "defense": "180.6",
        "equipment_type": "Shields",
        "can_be_sold": "X",
        "how_to_obtain": "Easter Event: Blacksmithing Tiered Craftabl"
      },
      "wikiTitle": "Easter Royale Shield Mk V",
      "wikiUrl": "https://swordbloxonlinerebirth.fandom.com/wiki/Easter_Royale_Shield_Mk_V",
      "slot": "shield"
    },
    {
      "name": "Integrity Petal Shield",
      "levelReq": 1,
      "defense": 0.6,
      "dexterity": null,
      "worth": 1,
      "howToObtain": "Floor 1 Shop, Requires [[Integrity Petal Gamepass]",
      "raw": {
        "title1": "Integrity Petal Shield",
        "image1": "IntegrityPetalShield.png",
        "equipment_type": "Shields",
        "level_req": "Level 1 [Min]\nLevel 150 [Max]",
        "defense": "0.6[Min]\n144.9[Max]",
        "craftable": "X",
        "tradable": "X",
        "worth": "1 Col",
        "can_be_sold": "X",
        "how_to_obtain": "Floor 1 Shop, Requires [[Integrity Petal Gamepass]"
      },
      "wikiTitle": "Integrity Petal Shield",
      "wikiUrl": "https://swordbloxonlinerebirth.fandom.com/wiki/Integrity_Petal_Shield",
      "slot": "shield"
    },
    {
      "name": "Wooden Shield",
      "levelReq": 1,
      "defense": 0.6,
      "dexterity": null,
      "worth": 380,
      "howToObtain": "Starter Inventory, [[Shops#Floor 1 Shop|Floor 1 Shop]",
      "raw": {
        "title1": "Wooden Shield",
        "image1": "Wooden shield.png",
        "equipment_type": "Shields",
        "level_req": "Level 1",
        "craftable": "X",
        "tradable": "✔",
        "defense": "0.6",
        "worth": "380 Col",
        "can_be_sold": "✔",
        "how_to_obtain": "Starter Inventory, [[Shops#Floor 1 Shop|Floor 1 Shop]"
      },
      "wikiTitle": "Wooden Shield",
      "wikiUrl": "https://swordbloxonlinerebirth.fandom.com/wiki/Wooden_Shield",
      "slot": "shield"
    },
    {
      "name": "Titans Guard",
      "levelReq": 70,
      "defense": 45.9,
      "dexterity": null,
      "worth": 26600,
      "howToObtain": "Floor 7 Shop",
      "raw": {
        "title1": "Titans Guard",
        "image1": "Tirans Guard.png",
        "level_req": "Level 70",
        "craftable": "X",
        "tradable": "✔",
        "defense": "45.9",
        "equipment_type": "Shields",
        "worth": "26600 Col",
        "can_be_sold": "✔",
        "how_to_obtain": "Floor 7 Shop"
      },
      "wikiTitle": "Titans Guard",
      "wikiUrl": "https://swordbloxonlinerebirth.fandom.com/wiki/Titans_Guard",
      "slot": "shield"
    },
    {
      "name": "Sweet Shield",
      "levelReq": 150,
      "defense": 129.3,
      "dexterity": null,
      "worth": 57000,
      "howToObtain": "Floor 17 Shop",
      "raw": {
        "title1": "Sweet Shield",
        "image1": "Sweet shield.png",
        "equipment_type": "Shields",
        "level_req": "Level 150",
        "defense": "129.3",
        "craftable": "X",
        "tradable": "✔",
        "worth": "57000 Col",
        "can_be_sold": "✔",
        "how_to_obtain": "Floor 17 Shop"
      },
      "wikiTitle": "Sweet Shield",
      "wikiUrl": "https://swordbloxonlinerebirth.fandom.com/wiki/Sweet_Shield",
      "slot": "shield"
    },
    {
      "name": "Wafer Shield",
      "levelReq": 170,
      "defense": 153,
      "dexterity": null,
      "worth": 64600,
      "howToObtain": "[[Blacksmithing]",
      "raw": {
        "title1": "Wafer Shield",
        "image1": "Wafer Shield.png",
        "equipment_type": "Shields",
        "level_req": "Level 170",
        "craftable": "✔",
        "tradable": "✔",
        "defense": "153",
        "worth": "64600 Col",
        "can_be_sold": "✔",
        "how_to_obtain": "[[Blacksmithing]"
      },
      "wikiTitle": "Wafer Shield",
      "wikiUrl": "https://swordbloxonlinerebirth.fandom.com/wiki/Wafer_Shield",
      "slot": "shield"
    },
    {
      "name": "Summer Seashell Shield",
      "levelReq": 35,
      "defense": 18,
      "dexterity": null,
      "worth": 130,
      "howToObtain": "Summer Event: Summer Sho",
      "raw": {
        "title1": "Summer Seashell Shield",
        "image1": "Summer Seashell Shield.png",
        "equipment_type": "Shields",
        "level_req": "Level 35",
        "defense": "18",
        "craftable": "X",
        "tradable": "✔",
        "worth": "130 Seashell",
        "can_be_sold": "X",
        "how_to_obtain": "Summer Event: Summer Sho"
      },
      "wikiTitle": "Summer Seashell Shield",
      "wikiUrl": "https://swordbloxonlinerebirth.fandom.com/wiki/Summer_Seashell_Shield",
      "slot": "shield"
    },
    {
      "name": "Summer Seashell Shield Mk II",
      "levelReq": 70,
      "defense": 45.9,
      "dexterity": null,
      "worth": 230,
      "howToObtain": "Summer Event: Blacksmithing [2023",
      "raw": {
        "title1": "Summer Seashell Shield Mk II",
        "image1": "Summer Seashell Shield Mk II.png",
        "equipment_type": "Shields",
        "level_req": "Level 70",
        "defense": "45.9",
        "craftable": "✔",
        "tradable": "✔",
        "worth": "230 Seashell",
        "can_be_sold": "X",
        "how_to_obtain": "Summer Event: Blacksmithing [2023"
      },
      "wikiTitle": "Summer Seashell Shield Mk II",
      "wikiUrl": "https://swordbloxonlinerebirth.fandom.com/wiki/Summer_Seashell_Shield_Mk_II",
      "slot": "shield"
    },
    {
      "name": "Summer Seashell Shield Mk III",
      "levelReq": 105,
      "defense": 79.8,
      "dexterity": null,
      "worth": 330,
      "howToObtain": "Summer Event: Blacksmithing [2023",
      "raw": {
        "title1": "Summer Seashell Shield Mk III",
        "image1": "Summer Seashell Shield Mk III.png",
        "equipment_type": "Shields",
        "level_req": "Level 105",
        "defense": "79.8",
        "craftable": "✔",
        "tradable": "✔",
        "worth": "330 Seashell",
        "can_be_sold": "X",
        "how_to_obtain": "Summer Event: Blacksmithing [2023"
      },
      "wikiTitle": "Summer Seashell Shield Mk III",
      "wikiUrl": "https://swordbloxonlinerebirth.fandom.com/wiki/Summer_Seashell_Shield_Mk_III",
      "slot": "shield"
    },
    {
      "name": "Summer Seashell Shield Mk IV",
      "levelReq": 140,
      "defense": 117.6,
      "dexterity": null,
      "worth": 430,
      "howToObtain": "Summer Event: Blacksmithing [2023",
      "raw": {
        "title1": "Summer Seashell Shield Mk IV",
        "image1": "Summer Seashell Shield Mk IV.png",
        "equipment_type": "Shields",
        "level_req": "Level 140",
        "defense": "117.6",
        "craftable": "✔",
        "tradable": "✔",
        "worth": "430 Seashell",
        "can_be_sold": "X",
        "how_to_obtain": "Summer Event: Blacksmithing [2023"
      },
      "wikiTitle": "Summer Seashell Shield Mk IV",
      "wikiUrl": "https://swordbloxonlinerebirth.fandom.com/wiki/Summer_Seashell_Shield_Mk_IV",
      "slot": "shield"
    },
    {
      "name": "Summer Seashell Shield Mk V",
      "levelReq": 175,
      "defense": 159.3,
      "dexterity": null,
      "worth": 530,
      "howToObtain": "Summer Event: Blacksmithing [2023",
      "raw": {
        "title1": "Summer Seashell Shield Mk V",
        "image1": "Summer Seashell Shield Mk V.png",
        "equipment_type": "Shields",
        "level_req": "Level 175",
        "defense": "159.3",
        "craftable": "✔",
        "tradable": "✔",
        "worth": "530 Seashell",
        "can_be_sold": "X",
        "how_to_obtain": "Summer Event: Blacksmithing [2023"
      },
      "wikiTitle": "Summer Seashell Shield Mk V",
      "wikiUrl": "https://swordbloxonlinerebirth.fandom.com/wiki/Summer_Seashell_Shield_Mk_V",
      "slot": "shield"
    },
    {
      "name": "Summer Atlantean Shield Mk III",
      "levelReq": 105,
      "defense": 79.8,
      "dexterity": null,
      "worth": 340,
      "howToObtain": "Summer Event: Blacksmithin",
      "raw": {
        "title1": "Summer Atlantean Shield Mk III",
        "image1": "Summer Atlantean Shield Mk III.png",
        "equipment_type": "Shields",
        "level_req": "Level 105",
        "defense": "79.8",
        "craftable": "✔",
        "tradable": "✔",
        "worth": "340 Seashell",
        "can_be_sold": "X",
        "how_to_obtain": "Summer Event: Blacksmithin"
      },
      "wikiTitle": "Summer Atlantean Shield Mk III",
      "wikiUrl": "https://swordbloxonlinerebirth.fandom.com/wiki/Summer_Atlantean_Shield_Mk_III",
      "slot": "shield"
    },
    {
      "name": "Summer Atlantean Shield Mk IV",
      "levelReq": 140,
      "defense": 117.6,
      "dexterity": null,
      "worth": 440,
      "howToObtain": "Summer Event: Blacksmithin",
      "raw": {
        "title1": "Summer Atlantean Shield Mk IV",
        "image1": "Summer Atlantean Shield Mk IV.png",
        "equipment_type": "Shields",
        "level_req": "Level 140",
        "defense": "117.6",
        "craftable": "✔",
        "tradable": "✔",
        "worth": "440 Seashell",
        "can_be_sold": "X",
        "how_to_obtain": "Summer Event: Blacksmithin"
      },
      "wikiTitle": "Summer Atlantean Shield Mk IV",
      "wikiUrl": "https://swordbloxonlinerebirth.fandom.com/wiki/Summer_Atlantean_Shield_Mk_IV",
      "slot": "shield"
    },
    {
      "name": "Summer Atlantean Shield Mk V",
      "levelReq": 175,
      "defense": 159.3,
      "dexterity": null,
      "worth": 540,
      "howToObtain": "Summer Event: Blacksmithin",
      "raw": {
        "title1": "Summer Atlantean Shield Mk V",
        "image1": "Summer Atlantean Shield Mk V.png",
        "equipment_type": "Shields",
        "level_req": "Level 175",
        "defense": "159.3",
        "craftable": "✔",
        "tradable": "✔",
        "worth": "540 Seashell",
        "can_be_sold": "X",
        "how_to_obtain": "Summer Event: Blacksmithin"
      },
      "wikiTitle": "Summer Atlantean Shield Mk V",
      "wikiUrl": "https://swordbloxonlinerebirth.fandom.com/wiki/Summer_Atlantean_Shield_Mk_V",
      "slot": "shield"
    }
  ]
}